py_transgpt-2.1.dist-info/licenses/LICENSE.txt
transgpt/__init__.py
transgpt/_settings.py
transgpt/_trans_base.py
transgpt/trans_baidu.py
transgpt/trans_chatgpt.py
transgpt/trans_tencent.py
transgpt/translate.py
py_transgpt-2.1.dist-info/METADATA
py_transgpt-2.1.dist-info/WHEEL
py_transgpt-2.1.dist-info/top_level.txt
py_transgpt-2.1.dist-info/RECORD
