Metadata-Version: 2.4
Name: py-transgpt
Version: 2.1
Summary: Platform translation interface encapsulation: ChatGPT, Baidu, Tencent
Home-page: https://github.com/EXP-Codes/py-transgpt
Author: EXP
Author-email: exp.lqb@gmail.com
Project-URL: Bug Reports, https://github.com/EXP-Codes/py-transgpt/issues
Project-URL: Funding, https://github.com/EXP-Codes/py-transgpt/tree/master/imgs/donate-alipay.png
Project-URL: Say Thanks!, https://github.com/EXP-Codes/py-transgpt/tree/master/imgs/donate-wechat.png
Project-URL: Source, https://github.com/EXP-Codes/py-transgpt
Keywords: translation,ChatGPT,Baidu,Tencent
Classifier: Development Status :: 3 - Alpha
Classifier: Intended Audience :: Developers
Classifier: Topic :: Software Development :: Build Tools
Classifier: License :: OSI Approved :: MIT License
Classifier: Programming Language :: Python :: 3
Classifier: Programming Language :: Python :: 3.5
Classifier: Programming Language :: Python :: 3.6
Classifier: Programming Language :: Python :: 3.7
Classifier: Programming Language :: Python :: 3.8
Classifier: Programming Language :: Python :: 3 :: Only
Requires-Python: >=3.5, <4
License-File: LICENSE.txt
Requires-Dist: py-color-log>=1.0.4
Requires-Dist: requests>=2.22.0
Requires-Dist: openai==1.42.0
Requires-Dist: httpx==0.27.2
Requires-Dist: tencentcloud-sdk-python==3.0.681
Provides-Extra: dev
Requires-Dist: check-manifest; extra == "dev"
Provides-Extra: test
Requires-Dist: coverage; extra == "test"
Dynamic: author
Dynamic: author-email
Dynamic: classifier
Dynamic: description
Dynamic: description-content-type
Dynamic: home-page
Dynamic: keywords
Dynamic: license-file
Dynamic: project-url
Dynamic: provides-extra
Dynamic: requires-dist
Dynamic: requires-python
Dynamic: summary
